aliyunsdkkms/__init__.py
aliyunsdkkms/endpoint.py
aliyunsdkkms/request/__init__.py
aliyunsdkkms/request/v20160120/AsymmetricDecryptRequest.py
aliyunsdkkms/request/v20160120/AsymmetricEncryptRequest.py
aliyunsdkkms/request/v20160120/AsymmetricSignRequest.py
aliyunsdkkms/request/v20160120/AsymmetricVerifyRequest.py
aliyunsdkkms/request/v20160120/CancelKeyDeletionRequest.py
aliyunsdkkms/request/v20160120/CertificatePrivateKeyDecryptRequest.py
aliyunsdkkms/request/v20160120/CertificatePrivateKeySignRequest.py
aliyunsdkkms/request/v20160120/CertificatePublicKeyEncryptRequest.py
aliyunsdkkms/request/v20160120/CertificatePublicKeyVerifyRequest.py
aliyunsdkkms/request/v20160120/ConnectKmsInstanceRequest.py
aliyunsdkkms/request/v20160120/CreateAliasRequest.py
aliyunsdkkms/request/v20160120/CreateApplicationAccessPointRequest.py
aliyunsdkkms/request/v20160120/CreateCertificateRequest.py
aliyunsdkkms/request/v20160120/CreateClientKeyRequest.py
aliyunsdkkms/request/v20160120/CreateKeyRequest.py
aliyunsdkkms/request/v20160120/CreateKeyVersionRequest.py
aliyunsdkkms/request/v20160120/CreateNetworkRuleRequest.py
aliyunsdkkms/request/v20160120/CreatePolicyRequest.py
aliyunsdkkms/request/v20160120/CreateSecretRequest.py
aliyunsdkkms/request/v20160120/DecryptRequest.py
aliyunsdkkms/request/v20160120/DeleteAliasRequest.py
aliyunsdkkms/request/v20160120/DeleteApplicationAccessPointRequest.py
aliyunsdkkms/request/v20160120/DeleteCertificateRequest.py
aliyunsdkkms/request/v20160120/DeleteClientKeyRequest.py
aliyunsdkkms/request/v20160120/DeleteKeyMaterialRequest.py
aliyunsdkkms/request/v20160120/DeleteNetworkRuleRequest.py
aliyunsdkkms/request/v20160120/DeletePolicyRequest.py
aliyunsdkkms/request/v20160120/DeleteSecretRequest.py
aliyunsdkkms/request/v20160120/DescribeAccountKmsStatusRequest.py
aliyunsdkkms/request/v20160120/DescribeApplicationAccessPointRequest.py
aliyunsdkkms/request/v20160120/DescribeCertificateRequest.py
aliyunsdkkms/request/v20160120/DescribeKeyRequest.py
aliyun_python_sdk_kms-2.16.4.dist-info/LICENSE
aliyun_python_sdk_kms-2.16.4.dist-info/METADATA
aliyun_python_sdk_kms-2.16.4.dist-info/WHEEL
aliyun_python_sdk_kms-2.16.4.dist-info/top_level.txt
aliyun_python_sdk_kms-2.16.4.dist-info/RECORD
